[{"code":27422,"strokeCount":28,"strokeOrder":[2,2,3,3,2,2,3,2,2,2,2,2,2,3,2,2,3,2,2,3,2,2,2,2,2,2,2,2]},{"code":29223,"strokeCount":28,"strokeOrder":[4,3,2,2,2,2,3,2,2,2,2,2,2,3,2,2,3,2,2,3,2,2,2,2,2,2,2,2]},{"code":32412,"strokeCount":28,"strokeOrder":[3,3,2,2,2,2,2,2,2,3,2,2,2,2,2,2,2,3,2,2,2,2,3,2,2,2,3,4]},{"code":35924,"strokeCount":28,"strokeOrder":[2,3,2,2,2,2,2,2,2,2,2,2,2,3,2,2,2,2,2,2,2,3,2,2,3,2,2,2]},{"code":38016,"strokeCount":28,"strokeOrder":[4,3,2,2,2,2,2,2,2,2,3,3,2,4,2,2,3,2,2,4,2,3,2,2,2,3,2,2]},{"code":38017,"strokeCount":28,"strokeOrder":[2,2,2,2,2,2,2,2,2,3,2,2,2,2,3,2,2,2,2,2,2,2,2,2,2,2,4,3]},{"code":38018,"strokeCount":28,"strokeOrder":[4,3,2,2,2,2,2,2,2,2,2,2,3,2,3,2,2,3,2,2,2,2,2,2,2,2,2,2]},{"code":40057,"strokeCount":28,"strokeOrder":[2,3,2,3,2,2,2,2,2,2,2,81,21,20,21,47,15,20,59,15,69,83,15,54,44,32,62,40]},{"code":40473,"strokeCount":28,"strokeOrder":[4,3,2,2,3,2,2,3,2,2,3,2,2,4,2,2,2,2,2,3,2,2,2,4,2,2,2,2]},{"code":40474,"strokeCount":28,"strokeOrder":[2,3,2,2,2,2,2,2,3,2,2,2,2,2,3,3,2,2,2,3,2,2,2,5,2,2,2,2]},{"code":40475,"strokeCount":28,"strokeOrder":[2,2,2,2,3,2,2,3,2,2,2,2,2,2,2,2,2,2,2,3,2,2,2,5,2,2,2,2]}]